discord_system_observer_bot/__init__.py
discord_system_observer_bot/__main__.py
discord_system_observer_bot/bot.py
discord_system_observer_bot/cli.py
discord_system_observer_bot/gpuinfo.py
discord_system_observer_bot/statsobserver.py
discord_system_observer_bot/sysinfo.py
discord_system_observer_bot/utils.py
discord_system_observer_bot-0.0.5.dist-info/LICENSE
discord_system_observer_bot-0.0.5.dist-info/METADATA
discord_system_observer_bot-0.0.5.dist-info/WHEEL
discord_system_observer_bot-0.0.5.dist-info/entry_points.txt
discord_system_observer_bot-0.0.5.dist-info/top_level.txt
discord_system_observer_bot-0.0.5.dist-info/RECORD
