Metadata-Version: 2.1
Name: discord-system-observer-bot
Version: 0.0.5
Summary: A Discord bot that observes a local machine, issues warnings and can be queries from Discord chat.
Home-page: https://github.com/Querela/discord-system-observer-bot
Author: Erik Körner
Author-email: koerner@informatik.uni-leipzig.de
License: MIT License
Keywords: discord,bot,system-observer
Platform: UNKNOWN
Classifier: Development Status :: 4 - Beta
Classifier: Environment :: Console
Classifier: License :: OSI Approved :: MIT License
Classifier: Operating System :: POSIX
Classifier: Programming Language :: Python :: 3
Classifier: Programming Language :: Python :: 3.6
Classifier: Programming Language :: Python :: 3.7
Classifier: Programming Language :: Python :: 3.8
Classifier: Topic :: Utilities
Requires-Python: >=3.6
Requires-Dist: discord.py
Requires-Dist: psutil
Provides-Extra: dev
Requires-Dist: black ; extra == 'dev'
Requires-Dist: pylint ; extra == 'dev'
Requires-Dist: twine ; extra == 'dev'
Requires-Dist: wheel ; extra == 'dev'
Provides-Extra: doc
Requires-Dist: pdoc3 ; extra == 'doc'
Provides-Extra: gpu
Requires-Dist: gputil ; extra == 'gpu'
Provides-Extra: plot
Requires-Dist: matplotlib ; extra == 'plot'
